MANIFEST.in
setup.py
django_appcache/__init__.py
django_appcache/helpers.py
django_appcache/models.py
django_appcache/settings.py
django_appcache/urls.py
django_appcache/views.py
django_appcache.egg-info/PKG-INFO
django_appcache.egg-info/SOURCES.txt
django_appcache.egg-info/dependency_links.txt
django_appcache.egg-info/top_level.txt
django_appcache/management/__init__.py
django_appcache/management/commands/__init__.py
django_appcache/management/commands/build_appcache.py
django_appcache/templates/__init__.py
django_appcache/templates/__init__.pyc
django_appcache/templates/django_appcache/manifest.appcache
django_appcache/templatetags/__init__.py
django_appcache/templatetags/django_appcache_tags.py