Metadata-Version: 1.0
Name: django-appcache
Version: 1.4
Summary: Build and serve an appcache manifest from Django.
Home-page: https://github.com/mozilla/django_appcache
Author: Kumar McMillan
Author-email: kumar.mcmillan@gmail.com
License: BSD
Platform: UNKNOWN
